<annotation>
	<folder>TEZRESIMLER</folder>
	<filename>50km98.JPG</filename>
	<path>D:\data\TEZRESIMLER\50km98.JPG</path>
	<source>
		<database>Unknown</database>
	</source>
	<size>
		<width>300</width>
		<height>670</height>
		<depth>3</depth>
	</size>
	<segmented>0</segmented>
	<object>
		<name>50 Km Hiz Siniri</name>
		<pose>Unspecified</pose>
		<truncated>0</truncated>
		<difficult>0</difficult>
		<bndbox>
			<xmin>113</xmin>
			<ymin>67</ymin>
			<xmax>263</xmax>
			<ymax>217</ymax>
		</bndbox>
	</object>
</annotation>
