<annotation>
	<folder>Yeni klasör</folder>
	<filename>cros2.JPG</filename>
	<path>D:\seniorprojectez\models\research\object_detection\images\Yeni klasör\cros2.JPG</path>
	<source>
		<database>Unknown</database>
	</source>
	<size>
		<width>1032</width>
		<height>643</height>
		<depth>3</depth>
	</size>
	<segmented>0</segmented>
	<object>
		<name>Yol Ver</name>
		<pose>Unspecified</pose>
		<truncated>0</truncated>
		<difficult>0</difficult>
		<bndbox>
			<xmin>824</xmin>
			<ymin>112</ymin>
			<xmax>939</xmax>
			<ymax>227</ymax>
		</bndbox>
	</object>
</annotation>
