<annotation>
	<folder>TEZRESIMLER</folder>
	<filename>IMG_2317.jpg</filename>
	<path>D:\data\TEZRESIMLER\IMG_2317.jpg</path>
	<source>
		<database>Unknown</database>
	</source>
	<size>
		<width>1080</width>
		<height>1440</height>
		<depth>3</depth>
	</size>
	<segmented>0</segmented>
	<object>
		<name>Kasisli Yol</name>
		<pose>Unspecified</pose>
		<truncated>0</truncated>
		<difficult>0</difficult>
		<bndbox>
			<xmin>732</xmin>
			<ymin>167</ymin>
			<xmax>886</xmax>
			<ymax>332</ymax>
		</bndbox>
	</object>
</annotation>
