<annotation>
	<folder>train</folder>
	<filename>IMG_5992.JPG</filename>
	<path>D:\seniorprojectez\models\research\object_detection\images\train\IMG_5992.JPG</path>
	<source>
		<database>Unknown</database>
	</source>
	<size>
		<width>1024</width>
		<height>1024</height>
		<depth>3</depth>
	</size>
	<segmented>0</segmented>
	<object>
		<name>Yol Ver</name>
		<pose>Unspecified</pose>
		<truncated>0</truncated>
		<difficult>0</difficult>
		<bndbox>
			<xmin>338</xmin>
			<ymin>155</ymin>
			<xmax>559</xmax>
			<ymax>340</ymax>
		</bndbox>
	</object>
</annotation>
